mitre_mcp_server/__init__.py
mitre_mcp_server/server.py
mitre_mcp_server/data/__init__.py
mitre_mcp_server/data/download.py
mitre_mcp_server/data/v18.1/enterprise-attack.json
mitre_mcp_server/data/v18.1/ics-attack.json
mitre_mcp_server/data/v18.1/mobile-attack.json
mitre_mcp_server-0.1.2.dist-info/METADATA
mitre_mcp_server-0.1.2.dist-info/WHEEL
mitre_mcp_server-0.1.2.dist-info/entry_points.txt
mitre_mcp_server-0.1.2.dist-info/RECORD
