Metadata-Version: 2.4
Name: mitre-mcp-server
Version: 0.1.2
Summary: MCP server providing access to MITRE ATT&CK threat intelligence framework
Author-email: Inoussa Mouiche <mouiche@uwindsor.ca>
License: Apache-2.0
Keywords: attack,cybersecurity,mcp,mitre,threat-intelligence
Classifier: Development Status :: 3 - Alpha
Classifier: Intended Audience :: Developers
Classifier: License :: OSI Approved :: Apache Software License
Classifier: Programming Language :: Python :: 3.12
Classifier: Topic :: Security
Requires-Python: >=3.12
Requires-Dist: httpx>=0.27.0
Requires-Dist: mcp>=1.1.0
Requires-Dist: mitreattack-python>=3.0.0
Requires-Dist: pydantic>=2.0.0
Requires-Dist: stix2>=3.0.0
